<step title="BackgroundTrace" date="2025-09-26T01:08:29.107" instance="d4288a" url="/api/zipdeploy" method="POST" >
  <step title="Creating temporary deployment - FetchDeploymentManager" date="2025-09-26T01:08:29.141" /><!-- duration: 1ms -->
  <step title="Creating temporary deployment" date="2025-09-26T01:08:29.145" /><!-- duration: 34ms -->
  <step title="Performing fetch based deployment" date="2025-09-26T01:08:29.193" >
    <step title="Cleaning up temp folders from previous zip deployments and extracting pushed zip file /tmp/zipdeploy/3cd1abac-e0be-4b54-b5e6-f807feabd960.zip (0.96 MB) to /tmp/zipdeploy/extracted" date="2025-09-26T01:08:30.291" >
      <step title="ChmodRecursive Process exited with total time taken in ms: 28" date="2025-09-26T01:08:30.379" /><!-- duration: 2ms -->
    </step><!-- duration: 91ms -->
    <step title="Deployment timer started" date="2025-09-26T01:08:32.386" >
      <step title="DeploymentManager.Deploy(id:ff32559a-6276-40fa-aed2-56a6070e471f)" date="2025-09-26T01:08:32.389" >
        <step title="Collecting changeset information" date="2025-09-26T01:08:32.397" /><!-- duration: 66ms -->
        <step title="Updating submodules" date="2025-09-26T01:08:32.466" /><!-- duration: 1096ms -->
        <step title="Determining deployment builder" date="2025-09-26T01:08:33.738" >
          <step title="Builder is OryxBuilder" date="2025-09-26T01:08:33.742" /><!-- duration: 2ms -->
        </step><!-- duration: 7ms -->
        <step title="PreDeployment: context.CleanOutputPath False" date="2025-09-26T01:08:33.790" >
          <step title="PreDeployment: context.OutputPath /home/site/wwwroot" date="2025-09-26T01:08:33.889" >
            <step title="Building" date="2025-09-26T01:08:33.986" >
              <step title="Executing external process" date="2025-09-26T01:08:34.227" type="process" path="bash" arguments="-c &quot;oryx build /tmp/zipdeploy/extracted -o /home/site/wwwroot --platform python --platform-version 3.11 -p virtualenv_name=antenv --log-file /tmp/build-debug.log  -i /tmp/8ddfc9936e2679b --compress-destination-dir | tee /tmp/oryx-build.log ; exit $PIPESTATUS &quot;" /><!-- duration: 10899ms -->
              <step title="Using PythonDeploymentLogParser" date="2025-09-26T01:08:45.400" /><!-- duration: 6ms -->
              <step title="Triggering recycle (preview mode disabled)." date="2025-09-26T01:08:46.300" /><!-- duration: 7ms -->
              <step title="Modified file to trigger a restart of the app container." date="2025-09-26T01:08:46.322" /><!-- duration: 2ms -->
              <step title="Skip function trigger and logicapp sync because function is not enabled." date="2025-09-26T01:08:46.326" /><!-- duration: 2ms -->
              <step title="Purge deployment items" date="2025-09-26T01:08:47.284" >
                <step title="Remove 95a7beea-, Success, received at 09/25/2025 22:44:41" date="2025-09-26T01:08:47.328" /><!-- duration: 2ms -->
              </step><!-- duration: 48ms -->
            </step><!-- duration: 13405ms -->
          </step><!-- duration: 13505ms -->
          <step title="Cleaning up temp files" date="2025-09-26T01:08:47.395" /><!-- duration: 1578ms -->
          <step title="Cleaning up temp files" date="2025-09-26T01:08:48.976" /><!-- duration: 510ms -->
          <step title="Reloading status file with latest updates" date="2025-09-26T01:08:49.503" >
            <step title="WebHooksManager.PublishEventAsync: PostDeployment" date="2025-09-26T01:08:49.508" /><!-- duration: 24ms -->
          </step><!-- duration: 31ms -->
          <step title="Cleaning up temporary deployment - fetch deployment was successful" date="2025-09-26T01:08:49.540" /><!-- duration: 3ms -->
        </step><!-- duration: 15791ms -->
      </step><!-- duration: 17204ms -->
